{
  "schemaVersion": 3,
  "updated": "2026-07-24T02:14:18.282844569Z",
  "mcDay": 8,
  "season": "Autumn",
  "trend": "SHOULDER",
  "today": {
    "condition": "Rain",
    "temp": 67,
    "feelsLike": 67,
    "wind": 17,
    "windDir": "NE",
    "humidity": 31,
    "tempUnit": "F",
    "windUnit": "mph"
  },
  "forecast": [
    {
      "condition": "Clear",
      "temp": 67,
      "feelsLike": 67,
      "wind": 2,
      "windDir": "E",
      "humidity": 17,
      "day": "+1"
    },
    {
      "condition": "Rain",
      "temp": 76,
      "feelsLike": 76,
      "wind": 20,
      "windDir": "E",
      "humidity": 51,
      "day": "+2"
    },
    {
      "condition": "Clear",
      "temp": 75,
      "feelsLike": 75,
      "wind": 27,
      "windDir": "SW",
      "humidity": 50,
      "day": "+3"
    }
  ],
  "alerts": [],
  "discussion": "Rain moves through Plains this autumn day, with a high near 67°F. Winds out of the NE around 17 mph. Looking ahead, tomorrow brings clear near 67°F.",
  "regions": [],
  "almanac": {
    "moonPhase": 0,
    "moonPhaseName": "Full Moon"
  },
  "biome": "minecraft:plains"
}